odoo/addons/stock_picking_group_by_partner_by_carrier_sale_line_position/README.rst
odoo/addons/stock_picking_group_by_partner_by_carrier_sale_line_position/__init__.py
odoo/addons/stock_picking_group_by_partner_by_carrier_sale_line_position/__manifest__.py
odoo/addons/stock_picking_group_by_partner_by_carrier_sale_line_position/i18n/stock_picking_group_by_partner_by_carrier_sale_line_position.pot
odoo/addons/stock_picking_group_by_partner_by_carrier_sale_line_position/models/__init__.py
odoo/addons/stock_picking_group_by_partner_by_carrier_sale_line_position/models/stock_picking.py
odoo/addons/stock_picking_group_by_partner_by_carrier_sale_line_position/readme/CONTRIBUTORS.rst
odoo/addons/stock_picking_group_by_partner_by_carrier_sale_line_position/readme/DESCRIPTION.rst
odoo/addons/stock_picking_group_by_partner_by_carrier_sale_line_position/report/report_deliveryslip.xml
odoo/addons/stock_picking_group_by_partner_by_carrier_sale_line_position/static/description/icon.png
odoo/addons/stock_picking_group_by_partner_by_carrier_sale_line_position/static/description/index.html
odoo13_addon_stock_picking_group_by_partner_by_carrier_sale_line_position-13.0.1.0.2.dist-info/METADATA
odoo13_addon_stock_picking_group_by_partner_by_carrier_sale_line_position-13.0.1.0.2.dist-info/WHEEL
odoo13_addon_stock_picking_group_by_partner_by_carrier_sale_line_position-13.0.1.0.2.dist-info/top_level.txt
odoo13_addon_stock_picking_group_by_partner_by_carrier_sale_line_position-13.0.1.0.2.dist-info/RECORD
